dataflow/__init__.py
dataflow/config.py
dataflow/hub_api.py
dataflow/logger.py
dataflow/sampler.py
dataflow/utils.py
dataflow/cloud/__init__.py
dataflow/cloud/cluster.py
dataflow/cloud/container.py
dataflow/cloud/iam_blocked_check.py
dataflow/cloud/logger.py
dataflow/collections/__init__.py
dataflow/collections/_store_version.py
dataflow/collections/client_manager.py
dataflow/collections/dataset/__init__.py
dataflow/collections/dataset/core.py
dataflow/collections/dataset/logger.py
dataflow/collections/tensor/__init__.py
dataflow/collections/tensor/core.py
dataflow/creds/__init__.py
dataflow/creds/aws.py
dataflow/creds/creds.py
dataflow/creds/logger.py
dataflow_gegham_test-0.9.0.dist-info/METADATA
dataflow_gegham_test-0.9.0.dist-info/WHEEL
dataflow_gegham_test-0.9.0.dist-info/top_level.txt
dataflow_gegham_test-0.9.0.dist-info/RECORD
