Metadata-Version: 2.1
Name: dataflow-gegham-test
Version: 0.9.0
Summary: Snark Hub
Home-page: https://github.com/snarkai/dataflow
Author: Snark AI Inc.
Author-email: support@snark.ai
License: UNKNOWN
Keywords: snark-hub
Platform: UNKNOWN
Requires-Python: >=3
Requires-Dist: awscli (==1.18.32)
Requires-Dist: botocore (==1.15.32)
Requires-Dist: boto3 (==1.12)
Requires-Dist: cython
Requires-Dist: dask[complete]
Requires-Dist: dask-cloudprovider
Requires-Dist: tenacity (<6,>=5.1.1)
Requires-Dist: pandas
Requires-Dist: distributed
Requires-Dist: nap (==2.0.0)
Requires-Dist: opencv-python
Requires-Dist: opencv-contrib-python
Requires-Dist: tqdm
Requires-Dist: requests
Requires-Dist: cachey
Requires-Dist: fsspec
Requires-Dist: s3fs
Requires-Dist: scipy (<2,>=1.4.1)
Requires-Dist: cryptography
Requires-Dist: ujson
Requires-Dist: pytest
Requires-Dist: flask
Requires-Dist: flask-cors
Requires-Dist: flask-httpauth
Requires-Dist: redis
Requires-Dist: graphviz (==0.14)
